watchpage/__init__.py
watchpage/command_line_options.py
watchpage/configuration.py
watchpage/constants.py
watchpage/main.py
watchpage/target.py
watchpage/samples/config_sample.yaml
watchpage/samples/dbeaver.yaml
watchpage/samples/muflone_apps.yaml
watchpage/samples/muflone_python.yaml
watchpage/samples/muflone_remmina.yaml
WatchPage-0.4.1.dist-info/LICENSE
WatchPage-0.4.1.dist-info/METADATA
WatchPage-0.4.1.dist-info/WHEEL
WatchPage-0.4.1.dist-info/entry_points.txt
WatchPage-0.4.1.dist-info/top_level.txt
WatchPage-0.4.1.dist-info/RECORD
