Metadata-Version: 2.1
Name: WatchPage
Version: 0.4.1
Summary: Watch webpages for changes
Home-page: http://www.muflone.com/watchpage/
Author: Fabio Castelli
Author-email: muflone@muflone.com
License: GPLv3+
Classifier: Development Status :: 1 - Planning
Classifier: Intended Audience :: Developers
Classifier: License :: OSI Approved :: GNU General Public License v3 or later (GPLv3+)
Classifier: Operating System :: OS Independent
Classifier: Programming Language :: Python :: 3
Classifier: Programming Language :: Python :: 3.9
Classifier: Programming Language :: Python :: 3.10
Classifier: Programming Language :: Python :: 3.11
Classifier: Topic :: Software Development :: Libraries :: Python Modules
License-File: LICENSE
Requires-Dist: pyyaml ==6.0.1
Requires-Dist: beautifulsoup4 ==4.12.2
Requires-Dist: lxml ==4.9.3
Requires-Dist: html5lib ==1.1
